oldmango.py
oldmango-0.71.dist-info/METADATA
oldmango-0.71.dist-info/WHEEL
oldmango-0.71.dist-info/entry_points.txt
oldmango-0.71.dist-info/top_level.txt
oldmango-0.71.dist-info/RECORD
