Metadata-Version: 2.1
Name: oldmango
Version: 0.71
Summary: Linux commands AI
Home-page: UNKNOWN
Author: UNKNOWN
Author-email: UNKNOWN
License: UNKNOWN
Platform: UNKNOWN
Requires-Dist: openai (==0.25.0)
Requires-Dist: click (==7.1.2)
Requires-Dist: requests (==2.26.0)
Requires-Dist: aiohttp
